{
  "last_updated": "2026-02-23",
  "entities": [
    {
      "id": "nasa",
      "name": "NASA",
      "image": "https://upload.wikimedia.org/wikipedia/commons/e/e5/NASA_logo.svg",
      "category": "government",
      "color": "#ff4d4d",
      "data": {
        "2025": {
          "income": {
            "total": 25383700000,
            "sources": [
              "U.S. Federal Budget Appropriations (Consolidated Appropriations Act)",
              "Reimbursable Services for Federal and Non-Federal Entities"
            ],
            "breakdown": {
              "federal_funding": {
                "name": "Federal Appropriations",
                "percent": 99.8
              },
              "other_revenue": {
                "name": "Reimbursable and Other Income",
                "percent": 0.2
              }
            }
          },
          "spending": {
            "total": 25383700000,
            "breakdown": {
              "deep_space_exploration": {
                "name": "Deep Space Exploration Systems (Artemis, SLS, Orion)",
                "percent": 30.01
              },
              "science": {
                "name": "Science (Earth Science, Planetary Science, Astrophysics)",
                "percent": 29.81
              },
              "space_operations": {
                "name": "Space Operations (ISS, Space Communications)",
                "percent": 17.29
              },
              "mission_support": {
                "name": "Safety, Security, and Mission Services",
                "percent": 12.00
              },
              "other_programs": {
                "name": "Space Technology, Aeronautics, STEM Engagement",
                "percent": 10.89
              }
            }
          },
          "methodology": "Data based on the FY 2025 President's Budget Request and subsequent Congressional Justifications. Total figure represents the enacted budget authority. Spending breakdown calculated by dividing major mission directorate allocations by the total topline figure."
        }
      }
    },
    {
      "id": "elon-musk",
      "name": "ELON MUSK",
      "image" : "https://cdn.geekwire.com/wp-content/uploads/2014/09/elonmusk-300x300.jpeg",
      "category": "person",
      "color": "#00ff88",
      "data": {
        "2025": {
          "income": {
            "total": 245000000000,
            "sources": [
              "Tesla Stock Options Restoration (Delaware Court Ruling)",
              "SpaceX Tender Offer Valuation Surge",
              "xAI Funding Rounds and Valuation Growth",
              "Tesla Market Capitalization Recovery"
            ],
            "breakdown": {
              "asset_appreciation_tesla": {
                "name": "Tesla Equity & Options Gains",
                "percent": 53.0
              },
              "spacex_valuation_growth": {
                "name": "SpaceX Private Equity Growth",
                "percent": 31.0
              },
              "xai_valuation_increase": {
                "name": "xAI Valuation Gains",
                "percent": 16.0
              }
            }
          },
          "spending": {
            "total": 21000000000,
            "sources": [
              "Tesla R&D and AI Infrastructure",
              "xAI Compute Power Acquisition",
              "SpaceX Starship Development",
              "Personal TSLA Share Purchases"
            ],
            "breakdown": {
              "ai_infrastructure_compute": {
                "name": "AI Infrastructure & Compute (xAI/Tesla)",
                "percent": 62.0
              },
              "aerospace_rd": {
                "name": "SpaceX Starship & Mars Program",
                "percent": 24.0
              },
              "direct_equity_reinvestment": {
                "name": "Direct TSLA Stock Purchases",
                "percent": 5.0
              },
              "other_ventures": {
                "name": "Neuralink/Boring Co & X Operations",
                "percent": 9.0
              }
            }
          },
          "methodology": "Income represents the net increase in wealth (approx. $245B) driven by the restoration of the 2018 Tesla pay package ($56B+), SpaceX valuation hitting $800B, and xAI reaching $200B+. Spending is calculated as a sum of estimated personal capital reinvestments and major Capex commitments in controlled entities (e.g., $13B for xAI compute and $8B for Tesla AI/robotics infrastructure)."
        }
      }
    }
  ]
}
